pytoxml
