Metadata-Version: 1.0
Name: pyToXml
Version: 0.9
Summary: Simple Python to XML library.
Home-page: https://github.com/skimhub/pyToXml.git
Author: Skimlinks
Author-email: dev@skimlinks.com
License: UNKNOWN
Keywords: python skimlinks xml dict array
Platform: UNKNOWN
